<?xml version="1.0" encoding="utf-8"?>
<!-- edited with XMLSPY v2004 rel. 2 U (http://www.xmlspy.com) by Ed Beach (Firaxis Games) -->
<GameData>
	<BaseGameText>
		<!-- Dido Diplo Text -->
		<Row Tag="LOC_DIPLO_ACCEPT_DECLARE_FRIEND_FROM_HUMAN_LEADER_DIDO_ANY">
			<Text>Ketika dua bangsa besar seperti kita memiliki kesepakatan yang sama, maka wajar jika kita menyebut mereka sebagai teman.</Text>
		</Row>
		<Row Tag="LOC_DIPLO_REJECT_DECLARE_FRIEND_FROM_HUMAN_LEADER_DIDO_ANY">
			<Text>Anda menyanjung diri sendiri. Phoenicia mengakui keberadaan bangsamu—tapi kami tidak mengakui persahabatan timbal balik.</Text>
		</Row>
		<Row Tag="LOC_DIPLO_DECLARE_FRIEND_FROM_AI_LEADER_DIDO_ANY">
			<Text>Datanglah, Yang Mulia, dan nyatakan kepada dunia bahwa Anda berdiri sebagai teman Phoenicia!</Text>
		</Row>
		<Row Tag="LOC_DIPLO_ACCEPT_DECLARE_FRIEND_FROM_AI_LEADER_DIDO_ANY">
			<Text>Ya. Ini aku bersumpah.</Text>
		</Row>
		<Row Tag="LOC_DIPLO_REJECT_DECLARE_FRIEND_FROM_AI_LEADER_DIDO_ANY">
			<Text>Saya tidak menyetujui hal ini.</Text>
		</Row>
		<Row Tag="LOC_DIPLO_ACCEPT_DELEGATION_FROM_HUMAN_LEADER_DIDO_ANY">
			<Text>Delegasi Anda diterima dan akan mendapat ketenangan bersama kami.</Text>
		</Row>
		<Row Tag="LOC_DIPLO_REJECT_DELEGATION_FROM_HUMAN_LEADER_DIDO_ANY">
			<Text>Phoenicia tidak memerlukan delegasi Anda, karena kami sudah mengetahui jumlah orang Anda.</Text>
		</Row>
		<Row Tag="LOC_DIPLO_DELEGATION_FROM_AI_LEADER_DIDO_ANY">
			<Text>Terimalah hadiah berupa murex ungu, cedar Lebanon, dan zaitun—sekadar cita rasa kekayaan Phoenicia.</Text>
		</Row>
		<Row Tag="LOC_DIPLO_DENOUNCE_FROM_HUMAN_LEADER_DIDO_ANY">
			<Text>Senator Anda menyerukan kehancuran kami dan Anda berani menyebut mereka sebagai orator? Anda berjalan buta menuju kehancuran Anda.</Text>
		</Row>
		<Row Tag="LOC_DIPLO_DENOUNCE_FROM_AI_LEADER_DIDO_ANY">
			<Text>Saya berdoa Anda dikirim ke dalam api demi Moloch! Saya berdoa agar Anda dijadikan persembahan kepada Mot! Saya berdoa Yam bangkit dan melahapmu! (Mencela Anda).</Text>
		</Row>
		<Row Tag="LOC_DIPLO_GREETING_LEADER_DIDO_ANY">
			<Text>Anda telah kembali. Selamat datang.</Text>
		</Row>
		<Row Tag="LOC_DIPLO_MAKE_ALLIANCE_FROM_AI_LEADER_DIDO_ANY">
			<Text>Anda telah adil dan benar terhadap Fenisia. Maukah Anda mengambil langkah selanjutnya dan menyatakan bahwa kita adalah sekutu?</Text>
		</Row>
		<Row Tag="LOC_DIPLO_MAKE_PEACE_AI_ACCEPT_DEAL_LEADER_DIDO_ANY">
			<Text>Anda telah menyampaikan maksud Anda. Mari kita berdamai, sebelum kita menghancurkan dunia.</Text>
		</Row>
		<Row Tag="LOC_DIPLO_MAKE_PEACE_AI_REFUSE_DEAL_LEADER_DIDO_ANY">
			<Text>Tidak. Anda bertanya dengan sia-sia.</Text>
		</Row>
		<Row Tag="LOC_DIPLO_MAKE_PEACE_FROM_AI_LEADER_DIDO_ANY">
			<Text>Aku menawarkanmu kedamaian—pilihan yang lebih membahagiakan daripada reruntuhan tembok dan nyanyian ratapan.</Text>
		</Row>
		<Row Tag="LOC_DIPLO_ACCEPT_OPEN_BORDERS_FROM_HUMAN_LEADER_DIDO_ANY">
			<Text>Ya. Menyeberang dengan bebas melalui tanah kami akan memperkaya rakyat kami.</Text>
		</Row>
		<Row Tag="LOC_DIPLO_REJECT_OPEN_BORDERS_FROM_HUMAN_LEADER_DIDO_ANY">
			<Text>Saya melihat tidak ada gunanya membiarkan unit Anda menginjak-injak tanah kami. Jangan melintasi perbatasan Fenisia.</Text>
		</Row>
		<Row Tag="LOC_DIPLO_OPEN_BORDERS_FROM_AI_LEADER_DIDO_ANY">
			<Text>Penekanan yang tidak masuk akal terhadap fiksi perbatasan hanya diperuntukkan bagi penguasa yang lebih rendah. Mari kita membuka perbatasan kita satu sama lain.</Text>
		</Row>
		<Row Tag="LOC_DIPLO_WARNING_TOO_MANY_TROOPS_NEAR_ME_LEADER_DIDO_ANY">
			<Text>Pengkhianatan apa yang kamu niatkan? Segera pindahkan pasukan Anda dari perbatasan kami.</Text>
		</Row>
		<Row Tag="LOC_DIPLO_DEFEAT_FROM_AI_LEADER_DIDO_ANY">
			<Text>Jangan bermegah atas penaklukan Anda. Suatu hari Anda mungkin melihat ibu kota Anda bermandikan api.</Text>
		</Row>
		<Row Tag="LOC_DIPLO_REJECT_MAKE_DEAL_FROM_AI_LEADER_DIDO_ANY">
			<Text>Saya tidak menyetujui hal ini.</Text>
		</Row>
		<Row Tag="LOC_DIPLO_ACCEPT_MAKE_DEAL_FROM_AI_LEADER_DIDO_ANY">
			<Text>Tawaran yang menyenangkan.</Text>
		</Row>
		<!--Eleanor England Diplo Text -->
		<Row Tag="LOC_DIPLO_ACCEPT_DECLARE_FRIEND_FROM_HUMAN_LEADER_ELEANOR_ENGLAND_ANY">
			<Text>Ya, Anda memang teman baik saya, dan saya senang mengenali Anda sebagai teman baik.</Text>
		</Row>
		<Row Tag="LOC_DIPLO_REJECT_DECLARE_FRIEND_FROM_HUMAN_LEADER_ELEANOR_ENGLAND_ANY">
			<Text>Kekaguman Anda menyanjung, tapi saya menolaknya. </Text>
		</Row>
		<Row Tag="LOC_DIPLO_DECLARE_FRIEND_FROM_AI_LEADER_ELEANOR_ENGLAND_ANY">
			<Text>Sangat sedikit orang yang memahami seni raja seperti kita. Tidakkah kita harus mengatakan kepada dunia bahwa kita berdiri sebagai teman?</Text>
		</Row>
		<Row Tag="LOC_DIPLO_ACCEPT_DECLARE_FRIEND_FROM_AI_LEADER_ELEANOR_ENGLAND_ANY">
			<Text>Bagaimana aku bisa menolak tawaran menarik seperti itu? </Text>
		</Row>
		<Row Tag="LOC_DIPLO_REJECT_DECLARE_FRIEND_FROM_AI_LEADER_ELEANOR_ENGLAND_ANY">
			<Text>Tidak, diberkatilah Anda.</Text>
		</Row>
		<Row Tag="LOC_DIPLO_ACCEPT_DELEGATION_FROM_HUMAN_LEADER_ELEANOR_ENGLAND_ANY">
			<Text>Delegasi Anda telah disambut sebagai tamu di istana saya. Saya akan mengirimi Anda salinan puisi yang ditulis untuk menandai peristiwa tersebut.</Text>
		</Row>
		<Row Tag="LOC_DIPLO_REJECT_DELEGATION_FROM_HUMAN_LEADER_ELEANOR_ENGLAND_ANY">
			<Text>Tarif yang remeh, ditawarkan dengan buruk, tidak mendapat tempat di pengadilan saya.</Text>
		</Row>
		<Row Tag="LOC_DIPLO_DELEGATION_FROM_AI_LEADER_ELEANOR_ENGLAND_ANY">
			<Text>Silakan menerima hadiah saya: vas kristal, anggur, truffle, dan selusin penyanyi untuk meramaikan istana Anda.</Text>
		</Row>
		<Row Tag="LOC_DIPLO_DENOUNCE_FROM_HUMAN_LEADER_ELEANOR_ENGLAND_ANY">
			<Text>Akan tiba saatnya ketika Anda membayar kesalahan Anda. Dan setelah itu, suatu saat ketika namamu hanya akan hidup sebagai penjahat dalam syair lucu.</Text>
		</Row>
		<Row Tag="LOC_DIPLO_DENOUNCE_FROM_AI_LEADER_ELEANOR_ENGLAND_ANY">
			<Text>Karena perbuatanmu hanya menghasilkan kegelapan dan tipu daya, Aku akan menentangmu—dan mendukung cinta dan tawa! (Mencela Anda).</Text>
		</Row>
		<Row Tag="LOC_DIPLO_GREETING_LEADER_ELEANOR_ENGLAND_ANY">
			<Text>Ah! Kami baru saja membicarakanmu.</Text>
		</Row>
		<Row Tag="LOC_DIPLO_MAKE_ALLIANCE_FROM_AI_LEADER_ELEANOR_ENGLAND_ANY">
			<Text>Bukankah kita sudah lama menemukan kesepakatan dalam urusan kita? Mari kita formalkan hal ini dengan aliansi.</Text>
		</Row>
		<Row Tag="LOC_DIPLO_MAKE_PEACE_AI_ACCEPT_DEAL_LEADER_ELEANOR_ENGLAND_ANY">
			<Text>Memperpanjang perang ini akan berubah dari keberanian yang terpuji menjadi pembantaian yang menyedihkan. Bergabunglah dengan saya dengan damai.</Text>
		</Row>
		<Row Tag="LOC_DIPLO_MAKE_PEACE_AI_REFUSE_DEAL_LEADER_ELEANOR_ENGLAND_ANY">
			<Text>Tentu saja tidak.</Text>
		</Row>
		<Row Tag="LOC_DIPLO_MAKE_PEACE_FROM_AI_LEADER_ELEANOR_ENGLAND_ANY">
			<Text>Selamat—kehebatan bela diri Anda terbukti. Apakah Anda memiliki hati yang damai, atau apakah ini adalah karakter Anda?</Text>
		</Row>
		<Row Tag="LOC_DIPLO_ACCEPT_OPEN_BORDERS_FROM_HUMAN_LEADER_ELEANOR_ENGLAND_ANY">
			<Text>Kalau begitu, biarkan perbatasan kita terbuka!</Text>
		</Row>
		<Row Tag="LOC_DIPLO_REJECT_OPEN_BORDERS_FROM_HUMAN_LEADER_ELEANOR_ENGLAND_ANY">
			<Text>Bukalah tanahku untuk mata-mata dan gelandanganmu? Tentu saja tidak. Puaslah dengan batasan Anda sendiri.</Text>
		</Row>
		<Row Tag="LOC_DIPLO_OPEN_BORDERS_FROM_AI_LEADER_ELEANOR_ENGLAND_ANY">
			<Text>Saya membuka tanah saya untuk unit-unit Anda yang akan melintasinya, tetapi saya juga meminta izin dari Anda.</Text>
		</Row>
		<Row Tag="LOC_DIPLO_WARNING_TOO_MANY_TROOPS_NEAR_ME_LEADER_ELEANOR_ENGLAND_ANY">
			<Text>Memamerkan kekuatan Anda dengan cara seperti itu menunjukkan kelemahan yang menyedihkan, dan bukan kekuatan. Pindahkan mereka dari perbatasan saya.</Text>
		</Row>
		<Row Tag="LOC_DIPLO_DEFEAT_FROM_AI_LEADER_ELEANOR_ENGLAND_ANY">
			<Text>Jika nafsumu akan kekuasaan mendorongmu untuk menghancurkan pemerintahanku, biarlah! Aku akan tetap memerintah istana cinta.</Text>
		</Row>
		<Row Tag="LOC_DIPLO_REJECT_MAKE_DEAL_FROM_AI_LEADER_ELEANOR_ENGLAND_ANY">
			<Text>Sungguh lucu! TIDAK.</Text>
		</Row>
		<Row Tag="LOC_DIPLO_ACCEPT_MAKE_DEAL_FROM_AI_LEADER_ELEANOR_ENGLAND_ANY">
			<Text>Persyaratan Anda bagus. Biarkan kanselir kami yang mengerjakan detailnya.</Text>
		</Row>
		<!--Eleanor France Diplo Text -->
		<Row Tag="LOC_DIPLO_ACCEPT_DECLARE_FRIEND_FROM_HUMAN_LEADER_ELEANOR_FRANCE_ANY">
			<Text>Ya, Anda memang teman baik saya, dan saya senang mengenali Anda sebagai teman baik.</Text>
		</Row>
		<Row Tag="LOC_DIPLO_REJECT_DECLARE_FRIEND_FROM_HUMAN_LEADER_ELEANOR_FRANCE_ANY">
			<Text>Kekaguman Anda menyanjung, tapi saya menolaknya. </Text>
		</Row>
		<Row Tag="LOC_DIPLO_DECLARE_FRIEND_FROM_AI_LEADER_ELEANOR_FRANCE_ANY">
			<Text>Sangat sedikit orang yang memahami seni raja seperti kita. Tidakkah kita harus mengatakan kepada dunia bahwa kita berdiri sebagai teman?</Text>
		</Row>
		<Row Tag="LOC_DIPLO_ACCEPT_DECLARE_FRIEND_FROM_AI_LEADER_ELEANOR_FRANCE_ANY">
			<Text>Bagaimana aku bisa menolak tawaran menarik seperti itu? </Text>
		</Row>
		<Row Tag="LOC_DIPLO_REJECT_DECLARE_FRIEND_FROM_AI_LEADER_ELEANOR_FRANCE_ANY">
			<Text>Tidak, diberkatilah Anda.</Text>
		</Row>
		<Row Tag="LOC_DIPLO_ACCEPT_DELEGATION_FROM_HUMAN_LEADER_ELEANOR_FRANCE_ANY">
			<Text>Delegasi Anda telah disambut sebagai tamu di istana saya. Saya akan mengirimi Anda salinan puisi yang ditulis untuk menandai peristiwa tersebut.</Text>
		</Row>
		<Row Tag="LOC_DIPLO_REJECT_DELEGATION_FROM_HUMAN_LEADER_ELEANOR_FRANCE_ANY">
			<Text>Tarif yang remeh, ditawarkan dengan buruk, tidak mendapat tempat di pengadilan saya.</Text>
		</Row>
		<Row Tag="LOC_DIPLO_DELEGATION_FROM_AI_LEADER_ELEANOR_FRANCE_ANY">
			<Text>Silakan menerima hadiah saya: vas kristal, anggur, truffle, dan selusin penyanyi untuk meramaikan istana Anda.</Text>
		</Row>
		<Row Tag="LOC_DIPLO_DENOUNCE_FROM_HUMAN_LEADER_ELEANOR_FRANCE_ANY">
			<Text>Akan tiba saatnya ketika Anda membayar kesalahan Anda. Dan setelah itu, suatu saat ketika namamu hanya akan hidup sebagai penjahat dalam syair lucu.</Text>
		</Row>
		<Row Tag="LOC_DIPLO_DENOUNCE_FROM_AI_LEADER_ELEANOR_FRANCE_ANY">
			<Text>Karena perbuatanmu hanya menghasilkan kegelapan dan tipu daya, Aku akan menentangmu—dan mendukung cinta dan tawa! (Mencela Anda).</Text>
		</Row>
		<Row Tag="LOC_DIPLO_GREETING_LEADER_ELEANOR_FRANCE_ANY">
			<Text>Ah! Kami baru saja membicarakanmu.</Text>
		</Row>
		<Row Tag="LOC_DIPLO_MAKE_ALLIANCE_FROM_AI_LEADER_ELEANOR_FRANCE_ANY">
			<Text>Bukankah kita sudah lama menemukan kesepakatan dalam urusan kita? Mari kita formalkan hal ini dengan aliansi.</Text>
		</Row>
		<Row Tag="LOC_DIPLO_MAKE_PEACE_AI_ACCEPT_DEAL_LEADER_ELEANOR_FRANCE_ANY">
			<Text>Memperpanjang perang ini akan berubah dari keberanian yang terpuji menjadi pembantaian yang menyedihkan. Bergabunglah dengan saya dengan damai.</Text>
		</Row>
		<Row Tag="LOC_DIPLO_MAKE_PEACE_AI_REFUSE_DEAL_LEADER_ELEANOR_FRANCE_ANY">
			<Text>Tentu saja tidak.</Text>
		</Row>
		<Row Tag="LOC_DIPLO_MAKE_PEACE_FROM_AI_LEADER_ELEANOR_FRANCE_ANY">
			<Text>Selamat—kehebatan bela diri Anda terbukti. Apakah Anda memiliki hati yang damai, atau apakah ini adalah karakter Anda?</Text>
		</Row>
		<Row Tag="LOC_DIPLO_ACCEPT_OPEN_BORDERS_FROM_HUMAN_LEADER_ELEANOR_FRANCE_ANY">
			<Text>Kalau begitu, biarkan perbatasan kita terbuka!</Text>
		</Row>
		<Row Tag="LOC_DIPLO_REJECT_OPEN_BORDERS_FROM_HUMAN_LEADER_ELEANOR_FRANCE_ANY">
			<Text>Bukalah tanahku untuk mata-mata dan gelandanganmu? Tentu saja tidak. Puaslah dengan batasan Anda sendiri.</Text>
		</Row>
		<Row Tag="LOC_DIPLO_OPEN_BORDERS_FROM_AI_LEADER_ELEANOR_FRANCE_ANY">
			<Text>Saya membuka tanah saya untuk unit-unit Anda yang akan melintasinya, tetapi saya juga meminta izin dari Anda.</Text>
		</Row>
		<Row Tag="LOC_DIPLO_WARNING_TOO_MANY_TROOPS_NEAR_ME_LEADER_ELEANOR_FRANCE_ANY">
			<Text>Memamerkan kekuatan Anda dengan cara seperti itu menunjukkan kelemahan yang menyedihkan, dan bukan kekuatan. Pindahkan mereka dari perbatasan saya.</Text>
		</Row>
		<Row Tag="LOC_DIPLO_DEFEAT_FROM_AI_LEADER_ELEANOR_FRANCE_ANY">
			<Text>Jika nafsumu akan kekuasaan mendorongmu untuk menghancurkan pemerintahanku, biarlah! Aku akan tetap memerintah istana cinta.</Text>
		</Row>
		<Row Tag="LOC_DIPLO_REJECT_MAKE_DEAL_FROM_AI_LEADER_ELEANOR_FRANCE_ANY">
			<Text>Sungguh lucu! TIDAK.</Text>
		</Row>
		<Row Tag="LOC_DIPLO_ACCEPT_MAKE_DEAL_FROM_AI_LEADER_ELEANOR_FRANCE_ANY">
			<Text>Persyaratan Anda bagus. Biarkan kanselir kami yang mengerjakan detailnya.</Text>
		</Row>
		<!--Kristina Diplo Text -->
		<Row Tag="LOC_DIPLO_ACCEPT_DECLARE_FRIEND_FROM_HUMAN_LEADER_KRISTINA_ANY">
			<Text>Aku menganggapmu sebagai teman! Saya akan dengan senang hati membagikan hal ini kepada dunia.</Text>
		</Row>
		<Row Tag="LOC_DIPLO_REJECT_DECLARE_FRIEND_FROM_HUMAN_LEADER_KRISTINA_ANY">
			<Text>Saya pikir Anda mengacaukan kekaguman Anda terhadap saya dengan persahabatan. Kami belum berteman. Mungkin suatu hari nanti.</Text>
		</Row>
		<Row Tag="LOC_DIPLO_DECLARE_FRIEND_FROM_AI_LEADER_KRISTINA_ANY">
			<Text>Maukah Anda bergabung dengan saya saat kita memberi tahu dunia bahwa negara kita bersahabat satu sama lain? Kami pasti akan menginspirasi mereka semua.</Text>
		</Row>
		<Row Tag="LOC_DIPLO_ACCEPT_DECLARE_FRIEND_FROM_AI_LEADER_KRISTINA_ANY">
			<Text>Saya setuju.</Text>
		</Row>
		<Row Tag="LOC_DIPLO_REJECT_DECLARE_FRIEND_FROM_AI_LEADER_KRISTINA_ANY">
			<Text>Ini tidak mungkin terjadi.</Text>
		</Row>
		<Row Tag="LOC_DIPLO_ACCEPT_DELEGATION_FROM_HUMAN_LEADER_KRISTINA_ANY">
			<Text>Saya akan menerima delegasi Anda, dan mereka akan tinggal sebagai tamu terhormat saya. Ahli drama saya memiliki karya baru untuk dibagikan kepada mereka.</Text>
		</Row>
		<Row Tag="LOC_DIPLO_REJECT_DELEGATION_FROM_HUMAN_LEADER_KRISTINA_ANY">
			<Text>Swedia tidak membutuhkan hal-hal sepele seperti ini.</Text>
		</Row>
		<Row Tag="LOC_DIPLO_DELEGATION_FROM_AI_LEADER_KRISTINA_ANY">
			<Text>Saya mengirimi Anda hadiah berupa stik bandy, acar ikan haring, lingonsylt, dan knäckebröd. Jangan makan tongkat bandy.</Text>
		</Row>
		<Row Tag="LOC_DIPLO_DENOUNCE_FROM_HUMAN_LEADER_KRISTINA_ANY">
			<Text>Aku akan memberitahu seluruh dunia tentang kejahatanmu, tentang kekasaranmu, tentang pengkhianatanmu!</Text>
		</Row>
		<Row Tag="LOC_DIPLO_DENOUNCE_FROM_AI_LEADER_KRISTINA_ANY">
			<Text>Di Swedia, kami memiliki banyak lagu daerah lucu yang menggambarkan Anda sebagai penjahat. Bahkan seni yang paling sederhana pun meniru kebenaran kehidupan. (Mencela Anda).</Text>
		</Row>
		<Row Tag="LOC_DIPLO_GREETING_LEADER_KRISTINA_ANY">
			<Text>Saya senang bertemu Anda lagi.</Text>
		</Row>
		<Row Tag="LOC_DIPLO_MAKE_ALLIANCE_FROM_AI_LEADER_KRISTINA_ANY">
			<Text>Saya percaya inilah saatnya kita menunjukkan kepada dunia keharmonisan hubungan kita, dan secara terbuka mendeklarasikan aliansi.</Text>
		</Row>
		<Row Tag="LOC_DIPLO_MAKE_PEACE_AI_ACCEPT_DEAL_LEADER_KRISTINA_ANY">
			<Text>Karena tidak satu pun dari kita mempertanyakan keberanian satu sama lain, mari kita berdamai secara bermartabat.</Text>
		</Row>
		<Row Tag="LOC_DIPLO_MAKE_PEACE_AI_REFUSE_DEAL_LEADER_KRISTINA_ANY">
			<Text>Tidak, saya tidak akan mengizinkan ini.</Text>
		</Row>
		<Row Tag="LOC_DIPLO_MAKE_PEACE_FROM_AI_LEADER_KRISTINA_ANY">
			<Text>Bukankah penderitaan rakyat kita menuntut kita berdamai sekarang?</Text>
		</Row>
		<Row Tag="LOC_DIPLO_ACCEPT_OPEN_BORDERS_FROM_HUMAN_LEADER_KRISTINA_ANY">
			<Text>Unit Anda dapat melewati Swedia tanpa hambatan.</Text>
		</Row>
		<Row Tag="LOC_DIPLO_REJECT_OPEN_BORDERS_FROM_HUMAN_LEADER_KRISTINA_ANY">
			<Text>Tidak, ini bukan kepentingan Swedia. Hormati perbatasan kita.</Text>
		</Row>
		<Row Tag="LOC_DIPLO_OPEN_BORDERS_FROM_AI_LEADER_KRISTINA_ANY">
			<Text>Ada banyak hal yang bisa kita peroleh dengan akses bebas melintasi perbatasan satu sama lain, setujukah Anda?</Text>
		</Row>
		<Row Tag="LOC_DIPLO_WARNING_TOO_MANY_TROOPS_NEAR_ME_LEADER_KRISTINA_ANY">
			<Text>Jangan gerakkan unit Anda naik turun di sepanjang perbatasan kami seperti anak kecil yang bermain dengan tentara mainan. Pindahkan mereka sekarang.</Text>
		</Row>
		<Row Tag="LOC_DIPLO_DEFEAT_FROM_AI_LEADER_KRISTINA_ANY">
			<Text>Saya tidak pernah menyukai kekuasaan, dan sekarang saya dibiarkan tanpa seni. Hanya penyesalan dan kehilangan yang tersisa bagiku.</Text>
		</Row>
		<Row Tag="LOC_DIPLO_REJECT_MAKE_DEAL_FROM_AI_LEADER_KRISTINA_ANY">
			<Text>Saya tidak bisa menerima tawaran ini.</Text>
		</Row>
		<Row Tag="LOC_DIPLO_ACCEPT_MAKE_DEAL_FROM_AI_LEADER_KRISTINA_ANY">
			<Text>Ini adalah pertukaran yang adil.</Text>
		</Row>
		<!-- Kupe Diplo Text -->
		<Row Tag="LOC_DIPLO_ACCEPT_DECLARE_FRIEND_FROM_HUMAN_LEADER_KUPE_ANY">
			<Text>Ya, kamu baik-baik saja. Kami Māori senang menjadi teman Anda.</Text>
		</Row>
		<Row Tag="LOC_DIPLO_REJECT_DECLARE_FRIEND_FROM_HUMAN_LEADER_KUPE_ANY">
			<Text>Ya, suku Māori belum siap untuk berteman dengan publik.</Text>
		</Row>
		<Row Tag="LOC_DIPLO_DECLARE_FRIEND_FROM_AI_LEADER_KUPE_ANY">
			<Text>Tentu saja ada orang yang lebih buruk dari Anda di dunia ini. Bolehkah aku bilang pada yang lain kalau kamu bukan orang brengsek?</Text>
		</Row>
		<Row Tag="LOC_DIPLO_ACCEPT_DECLARE_FRIEND_FROM_AI_LEADER_KUPE_ANY">
			<Text>Tentu.</Text>
		</Row>
		<Row Tag="LOC_DIPLO_REJECT_DECLARE_FRIEND_FROM_AI_LEADER_KUPE_ANY">
			<Text>Tidak, menurutku tidak.</Text>
		</Row>
		<Row Tag="LOC_DIPLO_ACCEPT_DELEGATION_FROM_HUMAN_LEADER_KUPE_ANY">
			<Text>Anda menghormati kami dengan hadiah bagus ini, tanda mana Anda.</Text>
		</Row>
		<Row Tag="LOC_DIPLO_REJECT_DELEGATION_FROM_HUMAN_LEADER_KUPE_ANY">
			<Text>Tidak. Jangan kirimkan hadiahmu kepada kami. Kami tidak ingin ada kewajiban kepada Anda.</Text>
		</Row>
		<Row Tag="LOC_DIPLO_DELEGATION_FROM_AI_LEADER_KUPE_ANY">
			<Text>Ini hadiah pounamu, jubah korowai, dan belatung huhu. Ayolah, aku ingin melihatmu memakan belatung huhu. </Text>
		</Row>
		<Row Tag="LOC_DIPLO_DENOUNCE_FROM_HUMAN_LEADER_KUPE_ANY">
			<Text>Perilaku buruk Anda telah menentukan sejarah kita, jadi saya sangat senang bisa menyatakan hal ini kepada dunia.</Text>
		</Row>
		<Row Tag="LOC_DIPLO_DENOUNCE_FROM_AI_LEADER_KUPE_ANY">
			<Text>Dunia melihat tindakan Anda, dan mereka percaya apa yang telah kita ketahui sejak lama—bahwa di antara semua pemimpin, Andalah yang paling jahat. (Mencela Anda).</Text>
		</Row>
		<Row Tag="LOC_DIPLO_GREETING_LEADER_KUPE_ANY">
			<Text>Ten koe!</Text>
		</Row>
		<Row Tag="LOC_DIPLO_MAKE_ALLIANCE_FROM_AI_LEADER_KUPE_ANY">
			<Text>Kamu tidak terlalu buruk. Bagaimana perasaan Anda tentang aliansi?</Text>
		</Row>
		<Row Tag="LOC_DIPLO_MAKE_PEACE_AI_ACCEPT_DEAL_LEADER_KUPE_ANY">
			<Text>Jadi ternyata orang kita sama-sama pemberani dan tangguh. Mari kita coba perdamaian dan lihat bagaimana kelanjutannya.</Text>
		</Row>
		<Row Tag="LOC_DIPLO_MAKE_PEACE_AI_REFUSE_DEAL_LEADER_KUPE_ANY">
			<Text>Itu tidak akan terjadi.</Text>
		</Row>
		<Row Tag="LOC_DIPLO_MAKE_PEACE_FROM_AI_LEADER_KUPE_ANY">
			<Text>Anda memiliki keberanian untuk berperang, ini benar. Apakah Anda memiliki keberanian untuk perdamaian?</Text>
		</Row>
		<Row Tag="LOC_DIPLO_ACCEPT_OPEN_BORDERS_FROM_HUMAN_LEADER_KUPE_ANY">
			<Text>Itu cukup. Kami memiliki banyak dunia untuk dijelajahi di sisi lain negeri Anda.</Text>
		</Row>
		<Row Tag="LOC_DIPLO_REJECT_OPEN_BORDERS_FROM_HUMAN_LEADER_KUPE_ANY">
			<Text>Perbatasan ada karena suatu alasan. Tolong tetap berada di sisi Anda.</Text>
		</Row>
		<Row Tag="LOC_DIPLO_OPEN_BORDERS_FROM_AI_LEADER_KUPE_ANY">
			<Text>Saya menawarkan perbatasan terbuka dengan suku Māori, sebagai imbalan atas hak untuk melintasi tanah Anda tanpa ancaman.</Text>
		</Row>
		<Row Tag="LOC_DIPLO_WARNING_TOO_MANY_TROOPS_NEAR_ME_LEADER_KUPE_ANY">
			<Text>Mungkin Anda ingin memindahkan semua pasukan ke dekat tanah Māori? Sebelum sesuatu yang buruk terjadi? Hanya sebuah pemikiran.</Text>
		</Row>
		<Row Tag="LOC_DIPLO_DEFEAT_FROM_AI_LEADER_KUPE_ANY">
			<Text>Saya telah melakukan yang terbaik, tetapi kekuatan Anda lebih besar. Setidaknya jantungku akan berdetak tak terkalahkan.</Text>
		</Row>
		<Row Tag="LOC_DIPLO_REJECT_MAKE_DEAL_FROM_AI_LEADER_KUPE_ANY">
			<Text>Ini adalah kesepakatan yang buruk.</Text>
		</Row>
		<Row Tag="LOC_DIPLO_ACCEPT_MAKE_DEAL_FROM_AI_LEADER_KUPE_ANY">
			<Text>Ya, itu akan berhasil.</Text>
		</Row>
		<!-- Laurier Diplo Text -->
		<Row Tag="LOC_DIPLO_ACCEPT_DECLARE_FRIEND_FROM_HUMAN_LEADER_LAURIER_ANY">
			<Text>Saya bergabung dengan masyarakat Kanada dalam keinginan mereka untuk menerima persahabatan Anda. Mari kita nyatakan hal ini kepada dunia!</Text>
		</Row>
		<Row Tag="LOC_DIPLO_REJECT_DECLARE_FRIEND_FROM_HUMAN_LEADER_LAURIER_ANY">
			<Text>Meskipun Anda mendapatkan rasa hormat dari saya, dan rasa hormat dari masyarakat Kanada, ini belum waktunya untuk menyatakan persahabatan yang langgeng.</Text>
		</Row>
		<Row Tag="LOC_DIPLO_DECLARE_FRIEND_FROM_AI_LEADER_LAURIER_ANY">
			<Text>Anda telah terbukti menjadi sahabat Kanada yang teguh dan setia. Maukah Anda membiarkan kami menyatakan kesepakatan bersama kepada dunia?</Text>
		</Row>
		<Row Tag="LOC_DIPLO_ACCEPT_DECLARE_FRIEND_FROM_AI_LEADER_LAURIER_ANY">
			<Text>Ya memang!</Text>
		</Row>
		<Row Tag="LOC_DIPLO_REJECT_DECLARE_FRIEND_FROM_AI_LEADER_LAURIER_ANY">
			<Text>Saya minta maaf, tidak.</Text>
		</Row>
		<Row Tag="LOC_DIPLO_ACCEPT_DELEGATION_FROM_HUMAN_LEADER_LAURIER_ANY">
			<Text>Terima kasih atas kebaikan delegasi Anda. Kami senang menerimanya.</Text>
		</Row>
		<Row Tag="LOC_DIPLO_REJECT_DELEGATION_FROM_HUMAN_LEADER_LAURIER_ANY">
			<Text>Kanada tidak membutuhkan hadiah yang remeh. Silakan tarik delegasi Anda.</Text>
		</Row>
		<Row Tag="LOC_DIPLO_DELEGATION_FROM_AI_LEADER_LAURIER_ANY">
			<Text>Masyarakat Kanada mempersembahkan hadiah berupa sirup maple, selimut wol, dan tutup kepala tradisional kami yang terhormat: Toque.</Text>
		</Row>
		<Row Tag="LOC_DIPLO_DENOUNCE_FROM_HUMAN_LEADER_LAURIER_ANY">
			<Text>Bernegosiasi dengan Anda menguji batas kesabaran manusia, dan saya tidak akan lagi menuruti perilaku Anda.</Text>
		</Row>
		<Row Tag="LOC_DIPLO_DENOUNCE_FROM_AI_LEADER_LAURIER_ANY">
			<Text>Saya berharap Anda terbukti menjadi penguasa yang lebih bijaksana dan menyenangkan, namun tindakan Anda membuat saya tidak punya harapan untuk masa depan yang damai. (Mencela Anda).</Text>
		</Row>
		<Row Tag="LOC_DIPLO_GREETING_LEADER_LAURIER_ANY">
			<Text>Saya senang bertemu Anda lagi.</Text>
		</Row>
		<Row Tag="LOC_DIPLO_MAKE_ALLIANCE_FROM_AI_LEADER_LAURIER_ANY">
			<Text>Kita mempunyai banyak bidang yang menjadi kepentingan bersama—bukankah hal-hal tersebut akan terlayani dengan baik jika kita membentuk aliansi?</Text>
		</Row>
		<Row Tag="LOC_DIPLO_MAKE_PEACE_AI_ACCEPT_DEAL_LEADER_LAURIER_ANY">
			<Text>Mengapa kita harus memperpanjang penderitaan dan mengobarkan kebencian? Mari kita akhiri perang ini dan berdamai.</Text>
		</Row>
		<Row Tag="LOC_DIPLO_MAKE_PEACE_AI_REFUSE_DEAL_LEADER_LAURIER_ANY">
			<Text>Saya minta maaf, tidak.</Text>
		</Row>
		<Row Tag="LOC_DIPLO_MAKE_PEACE_FROM_AI_LEADER_LAURIER_ANY">
			<Text>Ada lebih banyak hal yang bisa diperoleh dengan menarik hati dan jiwa daripada dengan kekuatan senjata. Mari kita memiliki kedamaian.</Text>
		</Row>
		<Row Tag="LOC_DIPLO_ACCEPT_OPEN_BORDERS_FROM_HUMAN_LEADER_LAURIER_ANY">
			<Text>Saya senang menerima persetujuan Anda, dan menyambut unit Anda untuk melintasi tanah Kanada.</Text>
		</Row>
		<Row Tag="LOC_DIPLO_REJECT_OPEN_BORDERS_FROM_HUMAN_LEADER_LAURIER_ANY">
			<Text>Saya tidak dapat menerima proposal ini, karena Kanada tidak berkepentingan untuk mengizinkan Anda memasuki wilayah kami.</Text>
		</Row>
		<Row Tag="LOC_DIPLO_OPEN_BORDERS_FROM_AI_LEADER_LAURIER_ANY">
			<Text>Saya ingin mengusulkan kesepakatan bersama mengenai perbatasan terbuka di antara rakyat kita.</Text>
		</Row>
		<Row Tag="LOC_DIPLO_WARNING_TOO_MANY_TROOPS_NEAR_ME_LEADER_LAURIER_ANY">
			<Text>Para coureurs de bois membawakan saya kabar meresahkan tentang banyaknya pasukan di sepanjang perbatasan kita. Mungkin Anda bisa menariknya? </Text>
		</Row>
		<Row Tag="LOC_DIPLO_DEFEAT_FROM_AI_LEADER_LAURIER_ANY">
			<Text>Maka berakhirlah impian kita tentang Kanada yang mungkin bisa terwujud. Orang-orang kami baik hati. Memerintah dengan belas kasihan, dan belajar dari mereka.</Text>
		</Row>
		<Row Tag="LOC_DIPLO_REJECT_MAKE_DEAL_FROM_AI_LEADER_LAURIER_ANY">
			<Text>Proposal ini tidak akan menguntungkan kita.</Text>
		</Row>
		<Row Tag="LOC_DIPLO_ACCEPT_MAKE_DEAL_FROM_AI_LEADER_LAURIER_ANY">
			<Text>Saya menerima lamaran Anda, dengan ucapan terima kasih.</Text>
		</Row>
		<!-- Mansa Musa Diplo Text -->
		<Row Tag="LOC_DIPLO_ACCEPT_DECLARE_FRIEND_FROM_HUMAN_LEADER_MANSA_MUSA_ANY">
			<Text>Aku senang kamu memanggilku &quot;teman&quot;, karena aku menganggapmu sebagai temanku.</Text>
		</Row>
		<Row Tag="LOC_DIPLO_REJECT_DECLARE_FRIEND_FROM_HUMAN_LEADER_MANSA_MUSA_ANY">
			<Text>Antusiasme Anda melebihi kenyataan situasi kami. Saya belum bisa menyebut Anda sebagai teman Mali.</Text>
		</Row>
		<Row Tag="LOC_DIPLO_DECLARE_FRIEND_FROM_AI_LEADER_MANSA_MUSA_ANY">
			<Text>Bukankah kita berdua mendapatkan banyak keuntungan dari ikatan kita? Haruskah kita memberitahu dunia bahwa kita berdiri sebagai teman?</Text>
		</Row>
		<Row Tag="LOC_DIPLO_ACCEPT_DECLARE_FRIEND_FROM_AI_LEADER_MANSA_MUSA_ANY">
			<Text>Ya! Puji Tuhan!</Text>
		</Row>
		<Row Tag="LOC_DIPLO_REJECT_DECLARE_FRIEND_FROM_AI_LEADER_MANSA_MUSA_ANY">
			<Text>Tidak mungkin demikian.</Text>
		</Row>
		<Row Tag="LOC_DIPLO_ACCEPT_DELEGATION_FROM_HUMAN_LEADER_MANSA_MUSA_ANY">
			<Text>Meski aku tak menginginkan apa pun, ketulusan pemberianmu adalah keberkahan tersendiri. Saya akan menerima delegasi Anda.</Text>
		</Row>
		<Row Tag="LOC_DIPLO_REJECT_DELEGATION_FROM_HUMAN_LEADER_MANSA_MUSA_ANY">
			<Text>Salomo, dalam kemegahannya, menolak hadiah dari Ratu Sheba, dan karena itu aku tidak boleh menerima hadiahmu.</Text>
		</Row>
		<Row Tag="LOC_DIPLO_DELEGATION_FROM_AI_LEADER_MANSA_MUSA_ANY">
			<Text>Terimalah hadiah sederhana berupa kain nila, teh Kikeliba, dan seratus kuli angkut yang membawa karung-karung berisi debu emas. </Text>
		</Row>
		<Row Tag="LOC_DIPLO_DENOUNCE_FROM_HUMAN_LEADER_MANSA_MUSA_ANY">
			<Text>Ular! Penggoda! Orang celaka! Pandanglah saat hukumanmu, karena itu akan segera tiba!</Text>
		</Row>
		<Row Tag="LOC_DIPLO_DENOUNCE_FROM_AI_LEADER_MANSA_MUSA_ANY">
			<Text>Ya Tuhan, mengapa Engkau mengizinkan orang yang berhati gelap ini memegang kekuasaan raja? Bring down your wrath, O heaven! (Mencela Anda).</Text>
		</Row>
		<Row Tag="LOC_DIPLO_GREETING_LEADER_MANSA_MUSA_ANY">
			<Text>Tolong, bicaralah.</Text>
		</Row>
		<Row Tag="LOC_DIPLO_MAKE_ALLIANCE_FROM_AI_LEADER_MANSA_MUSA_ANY">
			<Text>Akankah kita menjadi sekutu? Insya Allah Anda akan menjawab ya, dan kami akan mengumumkannya kepada dunia!</Text>
		</Row>
		<Row Tag="LOC_DIPLO_MAKE_PEACE_AI_ACCEPT_DEAL_LEADER_MANSA_MUSA_ANY">
			<Text>Waktunya telah tiba untuk mengesampingkan perang yang bodoh dan sia-sia ini, dan mewujudkan perdamaian di antara rakyat kita.</Text>
		</Row>
		<Row Tag="LOC_DIPLO_MAKE_PEACE_AI_REFUSE_DEAL_LEADER_MANSA_MUSA_ANY">
			<Text>Tidak, ini tidak bisa diterima.</Text>
		</Row>
		<Row Tag="LOC_DIPLO_MAKE_PEACE_FROM_AI_LEADER_MANSA_MUSA_ANY">
			<Text>Perang ini sia-sia dan tidak membuahkan hasil. Bukankah Tuhan lebih senang dengan perdamaian di antara kita?</Text>
		</Row>
		<Row Tag="LOC_DIPLO_ACCEPT_OPEN_BORDERS_FROM_HUMAN_LEADER_MANSA_MUSA_ANY">
			<Text>Ya, perjalanan gratis hanya bisa mendatangkan keberkahan bagi kami berdua.</Text>
		</Row>
		<Row Tag="LOC_DIPLO_REJECT_OPEN_BORDERS_FROM_HUMAN_LEADER_MANSA_MUSA_ANY">
			<Text>Ah, walaupun amal akan menuntunku untuk mengabulkan hal ini, kebijaksanaan menyatakan bahwa aku melarangnya untuk saat ini.</Text>
		</Row>
		<Row Tag="LOC_DIPLO_OPEN_BORDERS_FROM_AI_LEADER_MANSA_MUSA_ANY">
			<Text>Keinginan besarku adalah agar unit-unitku dapat melintasi perbatasanmu tanpa hambatan. Tolong, ijinkan hal ini terjadi.</Text>
		</Row>
		<Row Tag="LOC_DIPLO_WARNING_TOO_MANY_TROOPS_NEAR_ME_LEADER_MANSA_MUSA_ANY">
			<Text>Saya melihat Anda tidak perlu memamerkan pasukan besar Anda di perbatasan Mali. Silakan hapus sekarang.</Text>
		</Row>
		<Row Tag="LOC_DIPLO_DEFEAT_FROM_AI_LEADER_MANSA_MUSA_ANY">
			<Text>Kekayaan cepat berlalu; belajar adalah kesia-siaan. Semua yang telah kulakukan, ya Tuhan, kulakukan atas nama-Mu.</Text>
		</Row>
		<Row Tag="LOC_DIPLO_REJECT_MAKE_DEAL_FROM_AI_LEADER_MANSA_MUSA_ANY">
			<Text>Ini adalah tawaran yang tidak layak.</Text>
		</Row>
		<Row Tag="LOC_DIPLO_ACCEPT_MAKE_DEAL_FROM_AI_LEADER_MANSA_MUSA_ANY">
			<Text>Puji Tuhan, ini akan saya terima.</Text>
		</Row>
		<!-- Matthias Corvinus Diplo Text -->
		<Row Tag="LOC_DIPLO_ACCEPT_DECLARE_FRIEND_FROM_HUMAN_LEADER_MATTHIAS_CORVINUS_ANY">
			<Text>Ya! Hanya sedikit penguasa yang memahami beban raja sebaik Anda. Saya senang memanggil Anda teman.</Text>
		</Row>
		<Row Tag="LOC_DIPLO_REJECT_DECLARE_FRIEND_FROM_HUMAN_LEADER_MATTHIAS_CORVINUS_ANY">
			<Text>Seorang raja harus memilih teman-temannya dengan sangat hati-hati. Ini bukan saatnya aku memanggilmu seperti itu.</Text>
		</Row>
		<Row Tag="LOC_DIPLO_DECLARE_FRIEND_FROM_AI_LEADER_MATTHIAS_CORVINUS_ANY">
			<Text>Bukankah kita memerintah atas dukungan rakyat dan kehendak Tuhan? Bukankah hal ini seharusnya mengikat kita sebagai sahabat sejati di hadapan dunia?</Text>
		</Row>
		<Row Tag="LOC_DIPLO_ACCEPT_DECLARE_FRIEND_FROM_AI_LEADER_MATTHIAS_CORVINUS_ANY">
			<Text>Ya, terima kasih kepada Tuhan.</Text>
		</Row>
		<Row Tag="LOC_DIPLO_REJECT_DECLARE_FRIEND_FROM_AI_LEADER_MATTHIAS_CORVINUS_ANY">
			<Text>Ini tidak mungkin.</Text>
		</Row>
		<Row Tag="LOC_DIPLO_ACCEPT_DELEGATION_FROM_HUMAN_LEADER_MATTHIAS_CORVINUS_ANY">
			<Text>Terima kasih atas anugerah delegasi Anda, dan semoga kemurahan hati Anda diberkati.</Text>
		</Row>
		<Row Tag="LOC_DIPLO_REJECT_DELEGATION_FROM_HUMAN_LEADER_MATTHIAS_CORVINUS_ANY">
			<Text>Kita tidak membutuhkan hadiah atau kewajiban tersirat dari mereka. Hongaria cukup kaya.</Text>
		</Row>
		<Row Tag="LOC_DIPLO_DELEGATION_FROM_AI_LEADER_MATTHIAS_CORVINUS_ANY">
			<Text>Aku mengirimimu hadiah layaknya seorang pangeran: Renda halus, panah yang dihiasi lambangmu, dan paprikash yang dibuat dari resep keluargaku.</Text>
		</Row>
		<Row Tag="LOC_DIPLO_DENOUNCE_FROM_HUMAN_LEADER_MATTHIAS_CORVINUS_ANY">
			<Text>Anda adalah ular pelanggar hukum, burung nasar yang suka menggenggam, yang akan melihat dunia gemetar ketakutan di hadapan Anda. Ketahuilah bahwa aku tidak akan pernah takut padamu!</Text>
		</Row>
		<Row Tag="LOC_DIPLO_DENOUNCE_FROM_AI_LEADER_MATTHIAS_CORVINUS_ANY">
			<Text>Anda mengejar kekuasaan—selalu dan hanya kekuasaan—tetapi Hongaria akan menolak Anda sampai akhir. (Mencela Anda).</Text>
		</Row>
		<Row Tag="LOC_DIPLO_GREETING_LEADER_MATTHIAS_CORVINUS_ANY">
			<Text>Kembalinya Anda menghormati saya.</Text>
		</Row>
		<Row Tag="LOC_DIPLO_MAKE_ALLIANCE_FROM_AI_LEADER_MATTHIAS_CORVINUS_ANY">
			<Text>Anda menghormati hak dan wewenang Hongaria, dan telah terbukti sebagai teman yang baik. Mari kita perkuat ikatan kita dengan aliansi.</Text>
		</Row>
		<Row Tag="LOC_DIPLO_MAKE_PEACE_AI_ACCEPT_DEAL_LEADER_MATTHIAS_CORVINUS_ANY">
			<Text>Baiklah, saya rasa kita berdua sudah membuktikan pendapat kita. Sekarang mari kita beralih ke belas kasihan dan perdamaian.</Text>
		</Row>
		<Row Tag="LOC_DIPLO_MAKE_PEACE_AI_REFUSE_DEAL_LEADER_MATTHIAS_CORVINUS_ANY">
			<Text>Tidak pernah, tidak pernah.</Text>
		</Row>
		<Row Tag="LOC_DIPLO_MAKE_PEACE_FROM_AI_LEADER_MATTHIAS_CORVINUS_ANY">
			<Text>Tidak ada belas kasihan dalam memperpanjang perang ini dan tidak ada keadilan dalam mencari penyebabnya. Mari kita berdamai.</Text>
		</Row>
		<Row Tag="LOC_DIPLO_ACCEPT_OPEN_BORDERS_FROM_HUMAN_LEADER_MATTHIAS_CORVINUS_ANY">
			<Text>Ya biarlah begitu. Terima kasih atas hak jalan terbuka.</Text>
		</Row>
		<Row Tag="LOC_DIPLO_REJECT_OPEN_BORDERS_FROM_HUMAN_LEADER_MATTHIAS_CORVINUS_ANY">
			<Text>Ini merupakan suatu pemaksaan dan tidak dapat diterima.</Text>
		</Row>
		<Row Tag="LOC_DIPLO_OPEN_BORDERS_FROM_AI_LEADER_MATTHIAS_CORVINUS_ANY">
			<Text>Berikanlah agar kami mempunyai hak untuk bergerak melintasi perbatasan Anda, dan saya akan memberikan hal yang sama kepada Anda.</Text>
		</Row>
		<Row Tag="LOC_DIPLO_WARNING_TOO_MANY_TROOPS_NEAR_ME_LEADER_MATTHIAS_CORVINUS_ANY">
			<Text>Pengintai pasukan saya telah menghabiskan waktu berhari-hari mengikuti kemajuan pasukan Anda di dekat perbatasan. Pindahkan mereka dari Hongaria.</Text>
		</Row>
		<Row Tag="LOC_DIPLO_DEFEAT_FROM_AI_LEADER_MATTHIAS_CORVINUS_ANY">
			<Text>Hari ini Anda meraih kemenangan, tetapi bisakah Anda mempertahankan apa yang telah Anda ambil? </Text>
		</Row>
		<Row Tag="LOC_DIPLO_REJECT_MAKE_DEAL_FROM_AI_LEADER_MATTHIAS_CORVINUS_ANY">
			<Text>Menerima tawaran ini merupakan suatu tindakan yang merendahkan martabat seorang pangeran.</Text>
		</Row>
		<Row Tag="LOC_DIPLO_ACCEPT_MAKE_DEAL_FROM_AI_LEADER_MATTHIAS_CORVINUS_ANY">
			<Text>Tawaran yang murah hati! Saya menerimanya dengan hati bersyukur.</Text>
		</Row>
		<!-- Pachacuti Diplo Text -->
		<Row Tag="LOC_DIPLO_ACCEPT_DECLARE_FRIEND_FROM_HUMAN_LEADER_PACHACUTI_ANY">
			<Text>Ya, kami sedekat saudara kandung, dan dunia harus mendengarnya.</Text>
		</Row>
		<Row Tag="LOC_DIPLO_REJECT_DECLARE_FRIEND_FROM_HUMAN_LEADER_PACHACUTI_ANY">
			<Text>Saya tahu Anda berusaha tampil mulia di hadapan dunia, tetapi Anda tidak boleh mengklaim persahabatan ini dengan saya.</Text>
		</Row>
		<Row Tag="LOC_DIPLO_DECLARE_FRIEND_FROM_AI_LEADER_PACHACUTI_ANY">
			<Text>Kita ibarat matahari dan bulan, memberi terang pada dunia. Haruskah kita menyatakan persahabatan?</Text>
		</Row>
		<Row Tag="LOC_DIPLO_ACCEPT_DECLARE_FRIEND_FROM_AI_LEADER_PACHACUTI_ANY">
			<Text>Ini sangat bagus.</Text>
		</Row>
		<Row Tag="LOC_DIPLO_REJECT_DECLARE_FRIEND_FROM_AI_LEADER_PACHACUTI_ANY">
			<Text>Saya tidak menerima ini.</Text>
		</Row>
		<Row Tag="LOC_DIPLO_ACCEPT_DELEGATION_FROM_HUMAN_LEADER_PACHACUTI_ANY">
			<Text>Delegasi Anda dan hadiahnya dipersilakan. Anda menghormati saya dengan kebajikan Anda.</Text>
		</Row>
		<Row Tag="LOC_DIPLO_REJECT_DELEGATION_FROM_HUMAN_LEADER_PACHACUTI_ANY">
			<Text>Bawalah delegasimu pergi dan jangan berani menunjukkan kasih sayang kepadaku.</Text>
		</Row>
		<Row Tag="LOC_DIPLO_DELEGATION_FROM_AI_LEADER_PACHACUTI_ANY">
			<Text>Terimalah hadiah wol alpaka dan pirus ini. Aku juga mengirimimu cuy—makanlah selagi panas.</Text>
		</Row>
		<Row Tag="LOC_DIPLO_DENOUNCE_FROM_HUMAN_LEADER_PACHACUTI_ANY">
			<Text>Simpering, orang bodoh yang berhati cuy! Tanyakan teman apa yang kamu miliki untuk melindungimu, karena kamu tidak mempunyai kekuatan untuk melindungi dirimu sendiri.</Text>
		</Row>
		<Row Tag="LOC_DIPLO_DENOUNCE_FROM_AI_LEADER_PACHACUTI_ANY">
			<Text>Kekuasaanmu kosong, tanahmu hina, rakyatmu tidak bermoral. Hari kehancuranmu akan segera tiba. (Mencela Anda).</Text>
		</Row>
		<Row Tag="LOC_DIPLO_GREETING_LEADER_PACHACUTI_ANY">
			<Text>Selamat datang. Anda mungkin mendekati saya.</Text>
		</Row>
		<Row Tag="LOC_DIPLO_MAKE_ALLIANCE_FROM_AI_LEADER_PACHACUTI_ANY">
			<Text>Anda telah terbukti terhormat dan menepati janji Anda. Mari kita perdalam kewajiban kita satu sama lain dan bersumpah aliansi.</Text>
		</Row>
		<Row Tag="LOC_DIPLO_MAKE_PEACE_AI_ACCEPT_DEAL_LEADER_PACHACUTI_ANY">
			<Text>Rakyat kita sangat menderita dalam perang ini. Mari kita berdamai sekarang.</Text>
		</Row>
		<Row Tag="LOC_DIPLO_MAKE_PEACE_AI_REFUSE_DEAL_LEADER_PACHACUTI_ANY">
			<Text>Ini tidak akan terjadi.</Text>
		</Row>
		<Row Tag="LOC_DIPLO_MAKE_PEACE_FROM_AI_LEADER_PACHACUTI_ANY">
			<Text>Tampaknya Anda mempunyai kecakapan dalam berperang. Apakah Anda juga memiliki hati yang damai?</Text>
		</Row>
		<Row Tag="LOC_DIPLO_ACCEPT_OPEN_BORDERS_FROM_HUMAN_LEADER_PACHACUTI_ANY">
			<Text>Saya memberikan izin kepada unit Anda untuk memasuki wilayah Inca.</Text>
		</Row>
		<Row Tag="LOC_DIPLO_REJECT_OPEN_BORDERS_FROM_HUMAN_LEADER_PACHACUTI_ANY">
			<Text>Anda tidak memiliki izin untuk melintasi perbatasan kami. Jangan meneruskan masalah ini.</Text>
		</Row>
		<Row Tag="LOC_DIPLO_OPEN_BORDERS_FROM_AI_LEADER_PACHACUTI_ANY">
			<Text>Saya perlu mengirim unit melintasi perbatasan Anda. Berikan izin ini kepadaku.</Text>
		</Row>
		<Row Tag="LOC_DIPLO_WARNING_TOO_MANY_TROOPS_NEAR_ME_LEADER_PACHACUTI_ANY">
			<Text>Tentaramu berputar seperti anjing di perbatasan kami. Apa maksudmu dengan ini? Hapus segera.</Text>
		</Row>
		<Row Tag="LOC_DIPLO_DEFEAT_FROM_AI_LEADER_PACHACUTI_ANY">
			<Text>Bagaimana caramu menggelapkan matahari? Aku memerintah dengan tekun dan penuh belas kasihan—pastikan kamu juga melakukan hal yang sama.</Text>
		</Row>
		<Row Tag="LOC_DIPLO_REJECT_MAKE_DEAL_FROM_AI_LEADER_PACHACUTI_ANY">
			<Text>Saya murah hati—tetapi tidak sampai pada tingkatan itu.</Text>
		</Row>
		<Row Tag="LOC_DIPLO_ACCEPT_MAKE_DEAL_FROM_AI_LEADER_PACHACUTI_ANY">
			<Text>Ya, Inca akan memberimu ini.</Text>
		</Row>
		<!-- Suleiman Diplo Text -->
		<Row Tag="LOC_DIPLO_ACCEPT_DECLARE_FRIEND_FROM_HUMAN_LEADER_SULEIMAN_ANY">
			<Text>Tuhan telah memberi Anda kebijaksanaan untuk melihat keselarasan kepentingan kita.</Text>
		</Row>
		<Row Tag="LOC_DIPLO_REJECT_DECLARE_FRIEND_FROM_HUMAN_LEADER_SULEIMAN_ANY">
			<Text>Siapa kamu yang mengaku berteman denganku? Anda tidak setara dengan saya, hanya pengagum setia.</Text>
		</Row>
		<Row Tag="LOC_DIPLO_DECLARE_FRIEND_FROM_AI_LEADER_SULEIMAN_ANY">
			<Text>Karena perilakumu terhadapku selalu baik, aku memberimu izin untuk menyatakan persahabatanku di depan umum.</Text>
		</Row>
		<Row Tag="LOC_DIPLO_ACCEPT_DECLARE_FRIEND_FROM_AI_LEADER_SULEIMAN_ANY">
			<Text>Saya memberikan ini kepada Anda.</Text>
		</Row>
		<Row Tag="LOC_DIPLO_REJECT_DECLARE_FRIEND_FROM_AI_LEADER_SULEIMAN_ANY">
			<Text>Apa? Tidak, tentu saja tidak.</Text>
		</Row>
		<Row Tag="LOC_DIPLO_ACCEPT_DELEGATION_FROM_HUMAN_LEADER_SULEIMAN_ANY">
			<Text>Saya telah menerima delegasi Anda. Pemberian mereka telah dimasukkan ke dalam perbendaharaan bersama dengan pemberian orang lain.</Text>
		</Row>
		<Row Tag="LOC_DIPLO_REJECT_DELEGATION_FROM_HUMAN_LEADER_SULEIMAN_ANY">
			<Text>Jika Anda mengirim delegasi, mereka akan dikembalikan ke gerbang. Jauhkan mereka—dan diri Anda sendiri—rasa malu ini.</Text>
		</Row>
		<Row Tag="LOC_DIPLO_DELEGATION_FROM_AI_LEADER_SULEIMAN_ANY">
			<Text>Saya mengirimi Anda hadiah berupa batu rubi, zamrud, kerajinan emas, dan banyak makanan lezat, serta chesnidjibashi yang akan mencicipi racunnya atas nama Anda.</Text>
		</Row>
		<Row Tag="LOC_DIPLO_DENOUNCE_FROM_HUMAN_LEADER_SULEIMAN_ANY">
			<Text>Kamu adalah mangsa ular beludak, serigala, burung nasar, hyena, tikus—segala sesuatu yang penuh kebencian dan kedengkian menuntutmu sebagai penguasa mereka.</Text>
		</Row>
		<Row Tag="LOC_DIPLO_DENOUNCE_FROM_AI_LEADER_SULEIMAN_ANY">
			<Text>Kekurangajaran dan kecerobohanmu hanya diperbolehkan sejauh itu merupakan pelajaran bagi dunia tentang bagaimana tidak memperlakukanku. (Mencela Anda).</Text>
		</Row>
		<Row Tag="LOC_DIPLO_GREETING_LEADER_SULEIMAN_ANY">
			<Text>Anda boleh berbicara sekarang.</Text>
		</Row>
		<Row Tag="LOC_DIPLO_MAKE_ALLIANCE_FROM_AI_LEADER_SULEIMAN_ANY">
			<Text>Prestise Anda dengan dunia akan meningkat pesat, jika Anda menerima aliansi dengan saya.</Text>
		</Row>
		<Row Tag="LOC_DIPLO_MAKE_PEACE_AI_ACCEPT_DEAL_LEADER_SULEIMAN_ANY">
			<Text>Anda harus mengakhiri perang di antara kita, karena jika memperpanjang masalah ini akan mengundang kehancuran dan ketidaksenangan Tuhan.</Text>
		</Row>
		<Row Tag="LOC_DIPLO_MAKE_PEACE_AI_REFUSE_DEAL_LEADER_SULEIMAN_ANY">
			<Text>Aku bosan dengan permainan ini.</Text>
		</Row>
		<Row Tag="LOC_DIPLO_MAKE_PEACE_FROM_AI_LEADER_SULEIMAN_ANY">
			<Text>Belas kasih menuntut agar keadaan perang di antara kita segera diakhiri.</Text>
		</Row>
		<Row Tag="LOC_DIPLO_ACCEPT_OPEN_BORDERS_FROM_HUMAN_LEADER_SULEIMAN_ANY">
			<Text>Saya menerima pengakuan Anda atas hak saya untuk melintasi tanah Anda. Dan saya memberi Anda izin untuk melewati tanah Ottoman.</Text>
		</Row>
		<Row Tag="LOC_DIPLO_REJECT_OPEN_BORDERS_FROM_HUMAN_LEADER_SULEIMAN_ANY">
			<Text>Saya satu-satunya penguasa yang memiliki klaim atas tanah saya, dan Anda tidak boleh melewati perbatasan saya. </Text>
		</Row>
		<Row Tag="LOC_DIPLO_OPEN_BORDERS_FROM_AI_LEADER_SULEIMAN_ANY">
			<Text>Anda harus membuka perbatasan Anda kepada saya, dan dengan melakukan hal itu saya akan memberi Anda hak istimewa serupa di tanah saya sendiri.</Text>
		</Row>
		<Row Tag="LOC_DIPLO_WARNING_TOO_MANY_TROOPS_NEAR_ME_LEADER_SULEIMAN_ANY">
			<Text>Jangan membuat pertunjukan bela diri di perbatasanku, karena itu berisiko membuatku marah. Sudah banyak orang di kerajaanku yang tersinggung atas namaku.</Text>
		</Row>
		<Row Tag="LOC_DIPLO_DEFEAT_FROM_AI_LEADER_SULEIMAN_ANY">
			<Text>Menghancurkan! Menghancurkan! Istanbul menjadi Iram Pilar, hanya diingat oleh para penyair melankolis.</Text>
		</Row>
		<Row Tag="LOC_DIPLO_REJECT_MAKE_DEAL_FROM_AI_LEADER_SULEIMAN_ANY">
			<Text>Mustahil.</Text>
		</Row>
		<Row Tag="LOC_DIPLO_ACCEPT_MAKE_DEAL_FROM_AI_LEADER_SULEIMAN_ANY">
			<Text>Saya kira saya bisa melakukan ini dengan semangat sedekah.</Text>
		</Row>
	</BaseGameText>
</GameData>
